{
  "scriptCompleted": true,
  "filesAnalyzed": 20,
  "filesSkipped": [],
  "results": [
    {
      "path": "docs/superpowers/plans/2026-05-26-manejo-guia-clinica.md",
      "language": "markdown",
      "fileCategory": "docs",
      "totalLines": 693,
      "nonEmptyLines": 531,
      "sections": [
        {
          "heading": "Guía clínica unificada (Manejo) — Implementation Plan",
          "level": 1,
          "line": 1
        },
        {
          "heading": "File map",
          "level": 2,
          "line": 15
        },
        {
          "heading": "Phase 1 — State, shell, patología (highest value)",
          "level": 2,
          "line": 37
        },
        {
          "heading": "Task 1: Guía session state + legacy migration",
          "level": 3,
          "line": 39
        },
        {
          "heading": "Task 2: Pathology step flattening (timeline data)",
          "level": 3,
          "line": 240
        },
        {
          "heading": "Task 3: Base CSS — reading + index rows",
          "level": 3,
          "line": 322
        },
        {
          "heading": "Task 4: Guía shell + wire `manejo.mjs` subtabs",
          "level": 3,
          "line": 435
        },
        {
          "heading": "Task 5: Patología — compact index + reading timeline",
          "level": 3,
          "line": 475
        },
        {
          "heading": "Phase 2 — Infusión mode",
          "level": 2,
          "line": 518
        },
        {
          "heading": "Task 6: Infusión index + reading",
          "level": 3,
          "line": 520
        },
        {
          "heading": "Phase 3 — Antibiótico mode",
          "level": 2,
          "line": 547
        },
        {
          "heading": "Task 7: ATB index + reading (culture banner collapsible)",
          "level": 3,
          "line": 549
        },
        {
          "heading": "Phase 4 — Navigation API, cleanup, regression",
          "level": 2,
          "line": 574
        },
        {
          "heading": "Task 8: Unified navigation helpers + legacy call sites",
          "level": 3,
          "line": 576
        },
        {
          "heading": "Task 9: Remove dead split/modal paths + CSS trim",
          "level": 3,
          "line": 632
        },
        {
          "heading": "Spec coverage self-review",
          "level": 2,
          "line": 663
        },
        {
          "heading": "Execution handoff",
          "level": 2,
          "line": 684
        }
      ],
      "metrics": {
        "importCount": 0,
        "exportCount": 0,
        "functionCount": 0,
        "classCount": 0,
        "sectionCount": 17
      }
    },
    {
      "path": "docs/superpowers/plans/2026-05-26-manejo-room-drive.md",
      "language": "markdown",
      "fileCategory": "docs",
      "totalLines": 612,
      "nonEmptyLines": 445,
      "sections": [
        {
          "heading": "Manejo modular + sala LAN persistente (room drive) — Implementation Plan",
          "level": 1,
          "line": 1
        },
        {
          "heading": "File structure",
          "level": 2,
          "line": 15
        },
        {
          "heading": "Phase A — Room drive (hacer antes de Fase B)",
          "level": 2,
          "line": 46
        },
        {
          "heading": "Task 1: `live-sync-membership.mjs`",
          "level": 3,
          "line": 48
        },
        {
          "heading": "Task 2: `live-sync-outbox.mjs`",
          "level": 3,
          "line": 166
        },
        {
          "heading": "Task 3: Host bundle incluye `manejo`",
          "level": 3,
          "line": 211
        },
        {
          "heading": "Task 4: `manejo-room-data.mjs`",
          "level": 3,
          "line": 257
        },
        {
          "heading": "Task 5: PUT host sin WS + outbox flush",
          "level": 3,
          "line": 301
        },
        {
          "heading": "Task 6: Membresía pegajosa + boot + reconnect",
          "level": 3,
          "line": 332
        },
        {
          "heading": "Task 7: Borrado paciente diferido + ⌘Z",
          "level": 3,
          "line": 382
        },
        {
          "heading": "Task 8: `updatedAt` en lab sets",
          "level": 3,
          "line": 432
        },
        {
          "heading": "Task 9: Ayuda + limpieza pendientes legacy (A′)",
          "level": 3,
          "line": 468
        },
        {
          "heading": "Phase B — Refactor Manejo (después de Phase A estable)",
          "level": 2,
          "line": 501
        },
        {
          "heading": "Task 10: Extraer `manejo-guia-context.mjs`",
          "level": 3,
          "line": 503
        },
        {
          "heading": "Task 11: Extraer electrolitos + SOME UI",
          "level": 3,
          "line": 520
        },
        {
          "heading": "Task 12: Extraer proto detail, editor, ATB UI",
          "level": 3,
          "line": 539
        },
        {
          "heading": "Task 13: Eliminar legacy renderers",
          "level": 3,
          "line": 556
        },
        {
          "heading": "Verification checklist (antes de cerrar epic)",
          "level": 2,
          "line": 575
        },
        {
          "heading": "Spec coverage (self-review)",
          "level": 2,
          "line": 587
        },
        {
          "heading": "Execution handoff",
          "level": 2,
          "line": 602
        }
      ],
      "metrics": {
        "importCount": 0,
        "exportCount": 0,
        "functionCount": 0,
        "classCount": 0,
        "sectionCount": 20
      }
    },
    {
      "path": "docs/superpowers/plans/2026-05-28-pitch-tour.md",
      "language": "markdown",
      "fileCategory": "docs",
      "totalLines": 233,
      "nonEmptyLines": 164,
      "sections": [
        {
          "heading": "Tour pitch (presentación) Implementation Plan",
          "level": 1,
          "line": 1
        },
        {
          "heading": "File map",
          "level": 2,
          "line": 15
        },
        {
          "heading": "Task 1: Visual layer (scrim + pitch spotlights + dock variant)",
          "level": 3,
          "line": 35
        },
        {
          "heading": "Task 2: Steps + targets",
          "level": 3,
          "line": 85
        },
        {
          "heading": "Task 3: Demo seed (cultivos S/I/R + EA 3 días)",
          "level": 3,
          "line": 106
        },
        {
          "heading": "Task 4: Pitch tour engine",
          "level": 3,
          "line": 134
        },
        {
          "heading": "Task 5: Integration",
          "level": 3,
          "line": 175
        },
        {
          "heading": "Task 6: Manual verification checklist",
          "level": 3,
          "line": 207
        },
        {
          "heading": "Plan self-review",
          "level": 2,
          "line": 221
        }
      ],
      "metrics": {
        "importCount": 0,
        "exportCount": 0,
        "functionCount": 0,
        "classCount": 0,
        "sectionCount": 9
      }
    },
    {
      "path": "docs/superpowers/plans/2026-05-28-tour-pitch-remediation.md",
      "language": "markdown",
      "fileCategory": "docs",
      "totalLines": 717,
      "nonEmptyLines": 537,
      "sections": [
        {
          "heading": "Tour pitch remediation Implementation Plan",
          "level": 1,
          "line": 1
        },
        {
          "heading": "File map",
          "level": 2,
          "line": 15
        },
        {
          "heading": "Task 1: Target metadata — `scrollPolicy`",
          "level": 3,
          "line": 34
        },
        {
          "heading": "Task 2: Badge text helper (callout-aligned)",
          "level": 3,
          "line": 105
        },
        {
          "heading": "Task 3: Spotlight gate + dock collapsed detection",
          "level": 3,
          "line": 178
        },
        {
          "heading": "Task 4: Wire dock collapse in settings-help",
          "level": 3,
          "line": 275
        },
        {
          "heading": "Task 5: Orchestrator refactor — `leaveStep` / `enterStep`",
          "level": 3,
          "line": 309
        },
        {
          "heading": "Task 6: Chart step (⑪) — modal z-index and no page scroll",
          "level": 3,
          "line": 403
        },
        {
          "heading": "Task 7: Cultivo history reconcile",
          "level": 3,
          "line": 446
        },
        {
          "heading": "Task 8: Harden patient restore — `exitPitchTour`",
          "level": 3,
          "line": 520
        },
        {
          "heading": "Task 9: CSS — minimized dock scroll",
          "level": 3,
          "line": 630
        },
        {
          "heading": "Task 10: Bundle + full test run",
          "level": 3,
          "line": 654
        },
        {
          "heading": "Task 11: Manual acceptance checklist",
          "level": 3,
          "line": 690
        },
        {
          "heading": "Spec coverage checklist",
          "level": 2,
          "line": 702
        }
      ],
      "metrics": {
        "importCount": 0,
        "exportCount": 0,
        "functionCount": 0,
        "classCount": 0,
        "sectionCount": 14
      }
    },
    {
      "path": "docs/superpowers/plans/2026-05-29-censo-pdf.md",
      "language": "markdown",
      "fileCategory": "docs",
      "totalLines": 472,
      "nonEmptyLines": 356,
      "sections": [
        {
          "heading": "Censo de guardia (PDF) — Implementation Plan",
          "level": 1,
          "line": 1
        },
        {
          "heading": "File map",
          "level": 2,
          "line": 15
        },
        {
          "heading": "Task 1: Helpers diagnósticos en paciente",
          "level": 3,
          "line": 43
        },
        {
          "heading": "Task 2: Formato ATB/Meds para censo",
          "level": 3,
          "line": 146
        },
        {
          "heading": "Task 3: Agregador `censo-build.mjs`",
          "level": 3,
          "line": 191
        },
        {
          "heading": "Task 4: PDF servidor `generate-censo.js`",
          "level": 3,
          "line": 229
        },
        {
          "heading": "Task 5: Mi Perfil — Equipo (R2 / R1)",
          "level": 3,
          "line": 292
        },
        {
          "heading": "Task 6: UI Datos del paciente (Sala)",
          "level": 3,
          "line": 322
        },
        {
          "heading": "Task 7: Export UI `censo-export.mjs`",
          "level": 3,
          "line": 345
        },
        {
          "heading": "Task 8: Nota y VPO — precarga (sin acoplar censo)",
          "level": 3,
          "line": 393
        },
        {
          "heading": "Task 9: Sync LAN / import paciente",
          "level": 3,
          "line": 419
        },
        {
          "heading": "Task 10: Verificación final",
          "level": 3,
          "line": 431
        },
        {
          "heading": "Spec coverage checklist",
          "level": 2,
          "line": 448
        },
        {
          "heading": "Notas de implementación",
          "level": 2,
          "line": 467
        }
      ],
      "metrics": {
        "importCount": 0,
        "exportCount": 0,
        "functionCount": 0,
        "classCount": 0,
        "sectionCount": 14
      }
    },
    {
      "path": "docs/superpowers/plans/2026-05-29-vpo.md",
      "language": "markdown",
      "fileCategory": "docs",
      "totalLines": 539,
      "nonEmptyLines": 398,
      "sections": [
        {
          "heading": "VPO (Valoración preoperatoria) Implementation Plan",
          "level": 1,
          "line": 1
        },
        {
          "heading": "File map",
          "level": 2,
          "line": 15
        },
        {
          "heading": "Task 1: Catálogos `vpo-lookups.mjs`",
          "level": 3,
          "line": 42
        },
        {
          "heading": "Task 2: Calculadora `vpo-calculator.mjs`",
          "level": 3,
          "line": 94
        },
        {
          "heading": "Task 3: Persistencia `vpoByPatient`",
          "level": 3,
          "line": 178
        },
        {
          "heading": "Task 4: Merge fármacos + labs/FC",
          "level": 3,
          "line": 262
        },
        {
          "heading": "Task 5: Catálogo fármacos perioperatorios",
          "level": 3,
          "line": 300
        },
        {
          "heading": "Task 6: Textos copiables `vpo-text.mjs`",
          "level": 3,
          "line": 332
        },
        {
          "heading": "Task 7: Expediente — HTML y tabs",
          "level": 3,
          "line": 361
        },
        {
          "heading": "Task 8: UI `vpo-panel.mjs`",
          "level": 3,
          "line": 421
        },
        {
          "heading": "Task 9: Backup, LAN, borrado paciente",
          "level": 3,
          "line": 468
        },
        {
          "heading": "Task 10: Estilos, build, verificación manual",
          "level": 3,
          "line": 489
        },
        {
          "heading": "Spec coverage (self-review)",
          "level": 2,
          "line": 515
        },
        {
          "heading": "Ejecución",
          "level": 2,
          "line": 532
        }
      ],
      "metrics": {
        "importCount": 0,
        "exportCount": 0,
        "functionCount": 0,
        "classCount": 0,
        "sectionCount": 14
      }
    },
    {
      "path": "docs/superpowers/plans/2026-05-30-clinical-calculator-safety.md",
      "language": "markdown",
      "fileCategory": "docs",
      "totalLines": 32,
      "nonEmptyLines": 19,
      "sections": [
        {
          "heading": "Clinical Calculator Safety Implementation Plan",
          "level": 1,
          "line": 1
        },
        {
          "heading": "Task 1: clinical-safety module — **DONE**",
          "level": 3,
          "line": 13
        },
        {
          "heading": "Task 2: manejo-calculators — **DONE**",
          "level": 3,
          "line": 18
        },
        {
          "heading": "Task 3: electrolyte-manejo — **DONE**",
          "level": 3,
          "line": 24
        },
        {
          "heading": "Task 4: Verify — **DONE**",
          "level": 3,
          "line": 29
        }
      ],
      "metrics": {
        "importCount": 0,
        "exportCount": 0,
        "functionCount": 0,
        "classCount": 0,
        "sectionCount": 5
      }
    },
    {
      "path": "docs/superpowers/plans/2026-05-30-clinical-conflict-resolution.md",
      "language": "markdown",
      "fileCategory": "docs",
      "totalLines": 848,
      "nonEmptyLines": 662,
      "sections": [
        {
          "heading": "Clinical Conflict Resolution Implementation Plan",
          "level": 1,
          "line": 1
        },
        {
          "heading": "File map",
          "level": 2,
          "line": 17
        },
        {
          "heading": "Task 0: Prerequisite gate",
          "level": 3,
          "line": 42
        },
        {
          "heading": "Task 1: Entity keys and host-store registry",
          "level": 3,
          "line": 61
        },
        {
          "heading": "Task 2: ConflictResolver core",
          "level": 3,
          "line": 146
        },
        {
          "heading": "Task 3: HTTP PUT /patients versioned envelope",
          "level": 3,
          "line": 324
        },
        {
          "heading": "Task 4: WebSocket hub — resolver + unicast conflict",
          "level": 3,
          "line": 402
        },
        {
          "heading": "Task 5: IndexedDB draft-conflict store",
          "level": 3,
          "line": 475
        },
        {
          "heading": "Task 6: versioned-mutation builder",
          "level": 3,
          "line": 550
        },
        {
          "heading": "Task 7: Clinical Diff Viewer modal",
          "level": 3,
          "line": 624
        },
        {
          "heading": "Task 8: Conflict orchestration in lan-sync",
          "level": 3,
          "line": 664
        },
        {
          "heading": "Task 9: Migrate LiveSync emitters to versioned envelopes",
          "level": 3,
          "line": 715
        },
        {
          "heading": "Task 10: lan-client events",
          "level": 3,
          "line": 764
        },
        {
          "heading": "Task 11: Draft recovery UI + bundle",
          "level": 3,
          "line": 791
        },
        {
          "heading": "Spec coverage checklist",
          "level": 2,
          "line": 822
        },
        {
          "heading": "Execution handoff",
          "level": 2,
          "line": 839
        }
      ],
      "metrics": {
        "importCount": 0,
        "exportCount": 0,
        "functionCount": 0,
        "classCount": 0,
        "sectionCount": 16
      }
    },
    {
      "path": "docs/superpowers/plans/2026-05-30-lan-host-concurrency.md",
      "language": "markdown",
      "fileCategory": "docs",
      "totalLines": 618,
      "nonEmptyLines": 448,
      "sections": [
        {
          "heading": "LAN host concurrency (Phase 3a) — Implementation Plan",
          "level": 1,
          "line": 1
        },
        {
          "heading": "File map",
          "level": 2,
          "line": 19
        },
        {
          "heading": "Task 1: Entity key helpers",
          "level": 2,
          "line": 53
        },
        {
          "heading": "Task 2: Audit log ring buffer",
          "level": 2,
          "line": 140
        },
        {
          "heading": "Task 3: Async atomic JSON + write queue",
          "level": 2,
          "line": 194
        },
        {
          "heading": "Task 4: Host state cache",
          "level": 2,
          "line": 277
        },
        {
          "heading": "Task 5: Server bundle merge engine",
          "level": 2,
          "line": 319
        },
        {
          "heading": "Task 6: v1→v2 migration",
          "level": 2,
          "line": 356
        },
        {
          "heading": "Task 7: Refactor `host-store.js`",
          "level": 2,
          "line": 374
        },
        {
          "heading": "Task 8: HTTP router 409 contracts",
          "level": 2,
          "line": 424
        },
        {
          "heading": "Task 9: Client `conflict-merge.mjs`",
          "level": 2,
          "line": 458
        },
        {
          "heading": "Task 10: Refactor `live-sync-room.mjs`",
          "level": 2,
          "line": 480
        },
        {
          "heading": "Task 11: Draft buffer in `storage.js`",
          "level": 2,
          "line": 498
        },
        {
          "heading": "Task 12: Clinical Diff panel",
          "level": 2,
          "line": 524
        },
        {
          "heading": "Task 13: Integrate `lan-sync.mjs`",
          "level": 2,
          "line": 543
        },
        {
          "heading": "Task 14: Renderer bundle + docs",
          "level": 2,
          "line": 578
        },
        {
          "heading": "Spec coverage self-review",
          "level": 2,
          "line": 595
        },
        {
          "heading": "Manual test plan (Phase 3a sign-off)",
          "level": 2,
          "line": 613
        }
      ],
      "metrics": {
        "importCount": 0,
        "exportCount": 0,
        "functionCount": 0,
        "classCount": 0,
        "sectionCount": 18
      }
    },
    {
      "path": "docs/superpowers/plans/2026-05-30-lan-security-hardening.md",
      "language": "markdown",
      "fileCategory": "docs",
      "totalLines": 956,
      "nonEmptyLines": 730,
      "sections": [
        {
          "heading": "LAN Security Hardening Implementation Plan",
          "level": 1,
          "line": 1
        },
        {
          "heading": "File map (create / modify)",
          "level": 2,
          "line": 15
        },
        {
          "heading": "Task 1: Secret redaction module",
          "level": 3,
          "line": 52
        },
        {
          "heading": "Task 2: Secure token bootstrap and host-state rehash",
          "level": 3,
          "line": 186
        },
        {
          "heading": "Task 3: Host store — no silent wipe on hash mismatch",
          "level": 3,
          "line": 359
        },
        {
          "heading": "Task 4: Bearer auth helper",
          "level": 3,
          "line": 416
        },
        {
          "heading": "Task 5: In-memory ticket store",
          "level": 3,
          "line": 461
        },
        {
          "heading": "Task 6: Auth router (tickets, exchange, host-status)",
          "level": 3,
          "line": 500
        },
        {
          "heading": "Task 7: Host router — Bearer only",
          "level": 3,
          "line": 552
        },
        {
          "heading": "Task 8: WebSocket first-frame authentication",
          "level": 3,
          "line": 581
        },
        {
          "heading": "Task 9: Server integration (bootstrap, rate limits, CORS, join route, redaction audit)",
          "level": 3,
          "line": 611
        },
        {
          "heading": "Task 10: Renderer — `lan-client` and `lan-join-link`",
          "level": 3,
          "line": 752
        },
        {
          "heading": "Task 11: Mobile join boot + `lan-sync` host UX",
          "level": 3,
          "line": 814
        },
        {
          "heading": "Task 12: Electron IPC and main process",
          "level": 3,
          "line": 859
        },
        {
          "heading": "Task 13: Bundle renderer and full verification",
          "level": 3,
          "line": 893
        },
        {
          "heading": "Spec coverage checklist (self-review)",
          "level": 2,
          "line": 926
        },
        {
          "heading": "Execution handoff",
          "level": 2,
          "line": 947
        }
      ],
      "metrics": {
        "importCount": 0,
        "exportCount": 0,
        "functionCount": 0,
        "classCount": 0,
        "sectionCount": 17
      }
    },
    {
      "path": "docs/superpowers/plans/2026-05-30-native-document-generation.md",
      "language": "markdown",
      "fileCategory": "docs",
      "totalLines": 731,
      "nonEmptyLines": 567,
      "sections": [
        {
          "heading": "Native Document Generation Implementation Plan",
          "level": 1,
          "line": 1
        },
        {
          "heading": "File map",
          "level": 2,
          "line": 13
        },
        {
          "heading": "Task 1: Dependencies and shared DOCX utilities",
          "level": 3,
          "line": 39
        },
        {
          "heading": "Task 2: Port `generate_listado.py` → `listado.js` (TDD)",
          "level": 3,
          "line": 175
        },
        {
          "heading": "Task 3: Port `generate_indicaciones.py`",
          "level": 3,
          "line": 292
        },
        {
          "heading": "Task 4: Port `generate_note.py`",
          "level": 3,
          "line": 321
        },
        {
          "heading": "Task 5: HTTP streaming layer + audit logging",
          "level": 3,
          "line": 347
        },
        {
          "heading": "Task 6: Electron IPC (approved output dir)",
          "level": 3,
          "line": 467
        },
        {
          "heading": "Task 7: `document-export-client.mjs`",
          "level": 3,
          "line": 530
        },
        {
          "heading": "Task 8: Wire UI call sites",
          "level": 3,
          "line": 629
        },
        {
          "heading": "Task 9: Remove Python from build and repo",
          "level": 3,
          "line": 671
        },
        {
          "heading": "Task 10: Verification checklist",
          "level": 3,
          "line": 705
        },
        {
          "heading": "Plan self-review (spec coverage)",
          "level": 2,
          "line": 716
        }
      ],
      "metrics": {
        "importCount": 0,
        "exportCount": 0,
        "functionCount": 0,
        "classCount": 0,
        "sectionCount": 13
      }
    },
    {
      "path": "docs/superpowers/plans/2026-05-30-r-plus-security-architecture-remediation-plan.md",
      "language": "markdown",
      "fileCategory": "docs",
      "totalLines": 237,
      "nonEmptyLines": 161,
      "sections": [
        {
          "heading": "R+ Security and Architecture Remediation Implementation Plan",
          "level": 1,
          "line": 1
        },
        {
          "heading": "Task 1: Medical Calculator Safety Fixes",
          "level": 3,
          "line": 13
        },
        {
          "heading": "Task 2: Secure Authentication (Remove 1234)",
          "level": 3,
          "line": 86
        },
        {
          "heading": "Task 3: Server Protection (Rate Limiting and Header Auth)",
          "level": 3,
          "line": 139
        },
        {
          "heading": "Task 4: Encrypted Storage Migration",
          "level": 3,
          "line": 174
        },
        {
          "heading": "Task 5: Native Document Generation",
          "level": 3,
          "line": 202
        },
        {
          "heading": "Task 6: Conflict-free Sync (CRDT)",
          "level": 3,
          "line": 223
        }
      ],
      "metrics": {
        "importCount": 0,
        "exportCount": 0,
        "functionCount": 0,
        "classCount": 0,
        "sectionCount": 7
      }
    },
    {
      "path": "docs/superpowers/plans/2026-05-30-static-clinical-history.md",
      "language": "markdown",
      "fileCategory": "docs",
      "totalLines": 43,
      "nonEmptyLines": 28,
      "sections": [
        {
          "heading": "Static Clinical History — Implementation Plan",
          "level": 1,
          "line": 1
        },
        {
          "heading": "Task 1: Rule Engine and JSON Schema Core",
          "level": 3,
          "line": 9
        },
        {
          "heading": "Task 2: Server Pipeline",
          "level": 3,
          "line": 16
        },
        {
          "heading": "Task 3: Audit",
          "level": 3,
          "line": 24
        },
        {
          "heading": "Task 4: Frontend",
          "level": 3,
          "line": 29
        },
        {
          "heading": "Task 5: Verification",
          "level": 3,
          "line": 36
        },
        {
          "heading": "Task 6: Python cleanup",
          "level": 3,
          "line": 41
        }
      ],
      "metrics": {
        "importCount": 0,
        "exportCount": 0,
        "functionCount": 0,
        "classCount": 0,
        "sectionCount": 7
      }
    },
    {
      "path": "docs/superpowers/plans/2026-05-31-clinical-access-dashboard.md",
      "language": "markdown",
      "fileCategory": "docs",
      "totalLines": 400,
      "nonEmptyLines": 327,
      "sections": [
        {
          "heading": "Clinical Access Controls & Shared Dashboard Implementation Plan (v1.9.1)",
          "level": 1,
          "line": 1
        },
        {
          "heading": "Task 1: SQLCipher Schema Migrations & Extensions",
          "level": 3,
          "line": 13
        },
        {
          "heading": "Task 2: P2P Transaction Cryptographic Signing",
          "level": 3,
          "line": 126
        },
        {
          "heading": "Task 3: Clinical Access Matrix (V1 Permissive Mode)",
          "level": 3,
          "line": 171
        },
        {
          "heading": "Task 4: UI Shared Grid & R4 Partitioning",
          "level": 3,
          "line": 208
        },
        {
          "heading": "Task 5: Dynamic Vitals Monitoring Loop",
          "level": 3,
          "line": 332
        }
      ],
      "metrics": {
        "importCount": 0,
        "exportCount": 0,
        "functionCount": 0,
        "classCount": 0,
        "sectionCount": 6
      }
    },
    {
      "path": "docs/superpowers/plans/2026-05-31-clinical-teams-handoff-v2.md",
      "language": "markdown",
      "fileCategory": "docs",
      "totalLines": 571,
      "nonEmptyLines": 435,
      "sections": [
        {
          "heading": "Clinical Teams, Entrega & Scope V2 Implementation Plan",
          "level": 1,
          "line": 1
        },
        {
          "heading": "File map (create / modify)",
          "level": 2,
          "line": 15
        },
        {
          "heading": "PR 1 — Schema + rotation cycles + Incoming preview",
          "level": 2,
          "line": 44
        },
        {
          "heading": "Task 1: Schema v2 migration",
          "level": 3,
          "line": 46
        },
        {
          "heading": "Task 2: Rotation DB API + IPC",
          "level": 3,
          "line": 138
        },
        {
          "heading": "Task 3: Renderer rotation + Incoming strip (preview lock)",
          "level": 3,
          "line": 249
        },
        {
          "heading": "PR 2 — Self-serve teams + Guardia on-call",
          "level": 2,
          "line": 301
        },
        {
          "heading": "Task 4: Teams DB + IPC",
          "level": 3,
          "line": 303
        },
        {
          "heading": "Task 5: Mi rotación UI",
          "level": 3,
          "line": 332
        },
        {
          "heading": "PR 3 — `evaluateClinicalScope` V2",
          "level": 2,
          "line": 346
        },
        {
          "heading": "Task 6: Scope engine",
          "level": 3,
          "line": 348
        },
        {
          "heading": "Task 7: Enforce chart lock on patient open",
          "level": 3,
          "line": 399
        },
        {
          "heading": "PR 4 — Censo | Entrega + modal + guardia upsert",
          "level": 2,
          "line": 410
        },
        {
          "heading": "Task 8: Guardia upsert IPC",
          "level": 3,
          "line": 412
        },
        {
          "heading": "Task 9: Entrega modal + eligibility",
          "level": 3,
          "line": 444
        },
        {
          "heading": "Task 10: Grid Censo | Entrega toggle",
          "level": 3,
          "line": 459
        },
        {
          "heading": "PR 5 — R4 Follow-up pin",
          "level": 2,
          "line": 490
        },
        {
          "heading": "Task 11: Follow-up sector",
          "level": 3,
          "line": 492
        },
        {
          "heading": "PR 6 — LAN sync (same release train, after PR 4)",
          "level": 2,
          "line": 506
        },
        {
          "heading": "Task 12: Replicate V2 tables on LAN merge",
          "level": 3,
          "line": 508
        },
        {
          "heading": "package.json test registration",
          "level": 2,
          "line": 523
        },
        {
          "heading": "Spec coverage checklist (self-review)",
          "level": 2,
          "line": 544
        },
        {
          "heading": "Manual test plan (post-PR 4)",
          "level": 2,
          "line": 565
        }
      ],
      "metrics": {
        "importCount": 0,
        "exportCount": 0,
        "functionCount": 0,
        "classCount": 0,
        "sectionCount": 23
      }
    },
    {
      "path": "docs/superpowers/plans/2026-05-31-guardia-letter-cycle-fix.md",
      "language": "markdown",
      "fileCategory": "docs",
      "totalLines": 964,
      "nonEmptyLines": 788,
      "sections": [
        {
          "heading": "Guardia Letter-Cycle Fix Implementation Plan",
          "level": 1,
          "line": 1
        },
        {
          "heading": "Task 1: Core cycle functions — `getCycleConfig`, `letterIndexForTeam`, `isOnCallToday`",
          "level": 3,
          "line": 13
        },
        {
          "heading": "Task 2: Update `salaLetterForTeamOrArea` to handle R1 sub-indices",
          "level": 3,
          "line": 183
        },
        {
          "heading": "Task 3: Modify `computeSalaAbcdefDeficitWrite` to use letter-cycle",
          "level": 3,
          "line": 245
        },
        {
          "heading": "Task 4: Modify `canR2SalaAbcdefDeficitWrite` to use letter-cycle",
          "level": 3,
          "line": 394
        },
        {
          "heading": "Task 5: Modify R3 cross-coverage in `evaluateClinicalScope`",
          "level": 3,
          "line": 464
        },
        {
          "heading": "Task 6: Update `listEntregaTargets` in Entrega modal",
          "level": 3,
          "line": 512
        },
        {
          "heading": "Task 7: Add rank display and editing to \"Mi rotación\" panel",
          "level": 3,
          "line": 693
        },
        {
          "heading": "Task 8: Dynamic letter dropdown in team creation form",
          "level": 3,
          "line": 807
        },
        {
          "heading": "Task 9: Remove `SALA_LETTERS` constant",
          "level": 3,
          "line": 912
        },
        {
          "heading": "Task 10: Full integration verification",
          "level": 3,
          "line": 937
        }
      ],
      "metrics": {
        "importCount": 0,
        "exportCount": 0,
        "functionCount": 0,
        "classCount": 0,
        "sectionCount": 11
      }
    },
    {
      "path": "docs/superpowers/plans/2026-05-31-historia-clinica-institutional-format.md",
      "language": "markdown",
      "fileCategory": "docs",
      "totalLines": 286,
      "nonEmptyLines": 202,
      "sections": [
        {
          "heading": "Historia Clínica Institutional Format — Implementation Plan",
          "level": 1,
          "line": 1
        },
        {
          "heading": "File map",
          "level": 2,
          "line": 17
        },
        {
          "heading": "Task 1: Narrative compiler (read coherence)",
          "level": 3,
          "line": 35
        },
        {
          "heading": "Task 2: Defaults, catalogs + legacy migration",
          "level": 3,
          "line": 110
        },
        {
          "heading": "Task 3: Safety scan string from nested APP",
          "level": 3,
          "line": 169
        },
        {
          "heading": "Task 4: Server validation — nested shape",
          "level": 3,
          "line": 187
        },
        {
          "heading": "Task 5: Checklist UI helper",
          "level": 3,
          "line": 201
        },
        {
          "heading": "Task 6: Panel — stepper (fast fill) + lectura mode",
          "level": 3,
          "line": 216
        },
        {
          "heading": "Task 7: Styles",
          "level": 3,
          "line": 251
        },
        {
          "heading": "Plan self-review",
          "level": 2,
          "line": 263
        },
        {
          "heading": "Verification",
          "level": 2,
          "line": 278
        }
      ],
      "metrics": {
        "importCount": 0,
        "exportCount": 0,
        "functionCount": 0,
        "classCount": 0,
        "sectionCount": 11
      }
    },
    {
      "path": "docs/superpowers/plans/2026-05-31-onboarding-overhaul.md",
      "language": "markdown",
      "fileCategory": "docs",
      "totalLines": 898,
      "nonEmptyLines": 702,
      "sections": [
        {
          "heading": "Onboarding Overhaul Implementation Plan",
          "level": 1,
          "line": 1
        },
        {
          "heading": "File map",
          "level": 2,
          "line": 15
        },
        {
          "heading": "Reviewer mitigations (incorporated)",
          "level": 2,
          "line": 33
        },
        {
          "heading": "Task 1: Onboarding curriculum module",
          "level": 3,
          "line": 45
        },
        {
          "heading": "Task 2: Wire tour-targets to curriculum",
          "level": 3,
          "line": 296
        },
        {
          "heading": "Task 3: Progress persistence module",
          "level": 3,
          "line": 367
        },
        {
          "heading": "Task 4: Dock — Anterior, Pausar, Continuar, chapter badge",
          "level": 3,
          "line": 476
        },
        {
          "heading": "Task 5: Idempotent ACTION_STEPS (lab_parse, servicio_default)",
          "level": 3,
          "line": 638
        },
        {
          "heading": "Task 6: Neo companion tour mode + hub module entry",
          "level": 3,
          "line": 685
        },
        {
          "heading": "Task 7: Aprender R+ hub UI",
          "level": 3,
          "line": 719
        },
        {
          "heading": "Task 8: Shorter intro modal copy",
          "level": 3,
          "line": 815
        },
        {
          "heading": "Task 9: Bundle, full test, release note line",
          "level": 3,
          "line": 839
        },
        {
          "heading": "Spec coverage (self-review)",
          "level": 2,
          "line": 875
        },
        {
          "heading": "Manual test checklist",
          "level": 2,
          "line": 890
        }
      ],
      "metrics": {
        "importCount": 0,
        "exportCount": 0,
        "functionCount": 0,
        "classCount": 0,
        "sectionCount": 14
      }
    },
    {
      "path": "docs/superpowers/plans/2026-05-31-perfil-farmacoterapeutico.md",
      "language": "markdown",
      "fileCategory": "docs",
      "totalLines": 599,
      "nonEmptyLines": 453,
      "sections": [
        {
          "heading": "Perfil farmacoterapéutico histórico — Implementation Plan",
          "level": 1,
          "line": 1
        },
        {
          "heading": "File map",
          "level": 2,
          "line": 16
        },
        {
          "heading": "Task 1: Núcleo — adherencia y claves",
          "level": 3,
          "line": 35
        },
        {
          "heading": "Task 2: Parse SOME mensual + merge Receta",
          "level": 3,
          "line": 190
        },
        {
          "heading": "Task 3: Persistencia",
          "level": 3,
          "line": 302
        },
        {
          "heading": "Task 4: Respaldo e importación",
          "level": 3,
          "line": 356
        },
        {
          "heading": "Task 5: CSS tabla unificada",
          "level": 3,
          "line": 381
        },
        {
          "heading": "Task 6: Markup subvista y modales",
          "level": 3,
          "line": 408
        },
        {
          "heading": "Task 7: Panel UI (`med-pharm-profile-panel.mjs`)",
          "level": 3,
          "line": 438
        },
        {
          "heading": "Task 8: Tabla unificada y interacción celda",
          "level": 3,
          "line": 506
        },
        {
          "heading": "Task 9: Integración final y regresión",
          "level": 3,
          "line": 537
        },
        {
          "heading": "Plan self-review (spec coverage)",
          "level": 2,
          "line": 570
        },
        {
          "heading": "Execution handoff",
          "level": 2,
          "line": 588
        }
      ],
      "metrics": {
        "importCount": 0,
        "exportCount": 0,
        "functionCount": 0,
        "classCount": 0,
        "sectionCount": 13
      }
    },
    {
      "path": "docs/superpowers/plans/2026-05-31-sala-clinico-navigation-eventualidades.md",
      "language": "markdown",
      "fileCategory": "docs",
      "totalLines": 251,
      "nonEmptyLines": 176,
      "sections": [
        {
          "heading": "Sala Clínico Navigation + Eventualidades — Implementation Plan",
          "level": 1,
          "line": 1
        },
        {
          "heading": "File map",
          "level": 2,
          "line": 15
        },
        {
          "heading": "Task 1: Expediente tabs — Sala without top Estado actual",
          "level": 3,
          "line": 31
        },
        {
          "heading": "Task 2: HTML — segments and mounts",
          "level": 3,
          "line": 106
        },
        {
          "heading": "Task 3: Pase board — render routing",
          "level": 3,
          "line": 137
        },
        {
          "heading": "Task 4: Eventualidades panel",
          "level": 3,
          "line": 156
        },
        {
          "heading": "Plan self-review",
          "level": 2,
          "line": 230
        },
        {
          "heading": "Verification",
          "level": 2,
          "line": 244
        }
      ],
      "metrics": {
        "importCount": 0,
        "exportCount": 0,
        "functionCount": 0,
        "classCount": 0,
        "sectionCount": 8
      }
    }
  ]
}